{
  "songName": "Wait",
  "songSubName": "",
  "authorName": "The Bbot",
  "beatsPerMinute": 125.01999664306641,
  "previewStartTime": 30,
  "previewDuration": 12,
  "coverImagePath": "",
  "environmentName": "TriangleEnvironment",
  "difficultyLevels": [
    {
      "difficulty": "Expert",
      "difficultyRank": 4,
      "audioPath": "Wait.ogg",
      "jsonPath": "Expert.json",
      "offset": 220,
      "oldOffset": 220
    },
    {
      "difficulty": "Hard",
      "difficultyRank": 4,
      "audioPath": "Wait.ogg",
      "jsonPath": "Hard.json",
      "offset": 220,
      "oldOffset": 220
    },
    {
      "difficulty": "Normal",
      "difficultyRank": 4,
      "audioPath": "Wait.ogg",
      "jsonPath": "Normal.json",
      "offset": 220,
      "oldOffset": 220
    }
  ]
}